en_core_web_sm/__init__.py
en_core_web_sm/meta.json
en_core_web_sm/en_core_web_sm-3.0.0/accuracy.json
en_core_web_sm/en_core_web_sm-3.0.0/config.cfg
en_core_web_sm/en_core_web_sm-3.0.0/meta.json
en_core_web_sm/en_core_web_sm-3.0.0/tokenizer
en_core_web_sm/en_core_web_sm-3.0.0/attribute_ruler/patterns
en_core_web_sm/en_core_web_sm-3.0.0/lemmatizer/lookups/lookups.bin
en_core_web_sm/en_core_web_sm-3.0.0/ner/cfg
en_core_web_sm/en_core_web_sm-3.0.0/ner/model
en_core_web_sm/en_core_web_sm-3.0.0/ner/moves
en_core_web_sm/en_core_web_sm-3.0.0/parser/cfg
en_core_web_sm/en_core_web_sm-3.0.0/parser/model
en_core_web_sm/en_core_web_sm-3.0.0/parser/moves
en_core_web_sm/en_core_web_sm-3.0.0/senter/cfg
en_core_web_sm/en_core_web_sm-3.0.0/senter/model
en_core_web_sm/en_core_web_sm-3.0.0/tagger/cfg
en_core_web_sm/en_core_web_sm-3.0.0/tagger/model
en_core_web_sm/en_core_web_sm-3.0.0/tok2vec/cfg
en_core_web_sm/en_core_web_sm-3.0.0/tok2vec/model
en_core_web_sm/en_core_web_sm-3.0.0/vocab/key2row
en_core_web_sm/en_core_web_sm-3.0.0/vocab/lookups.bin
en_core_web_sm/en_core_web_sm-3.0.0/vocab/strings.json
en_core_web_sm/en_core_web_sm-3.0.0/vocab/vectors
artk_ecws_mirror-3.0.0.dist-info/METADATA
artk_ecws_mirror-3.0.0.dist-info/WHEEL
artk_ecws_mirror-3.0.0.dist-info/top_level.txt
artk_ecws_mirror-3.0.0.dist-info/RECORD
